.gitignore
CHANGELOG.rst
LICENSE
README.rst
requirements.txt
run-tests.sh
setup.cfg
setup.py
sharedbuffers.nja
sharedbuffers/__init__.py
sharedbuffers/_version.py
sharedbuffers/mapped_struct.c
sharedbuffers/mapped_struct.pxd
sharedbuffers/mapped_struct.py
sharedbuffers/pool.py
sharedbuffers.egg-info/PKG-INFO
sharedbuffers.egg-info/SOURCES.txt
sharedbuffers.egg-info/dependency_links.txt
sharedbuffers.egg-info/not-zip-safe
sharedbuffers.egg-info/requires.txt
sharedbuffers.egg-info/top_level.txt
tests/__init__.py
tests/mapped_struct.py
tests/pool.py