Metadata-Version: 2.1
Name: sharedbuffers
Version: 1.2.1
Summary: Shared-memory structured buffers
Home-page: https://github.com/jampp/sharedbuffers/
Author: Jampp
Author-email: klauss@jampp.com
Maintainer: Claudio Freire
Maintainer-email: klauss@jampp.com
License: BSD 3-Clause
Classifier: Development Status :: 4 - Beta
Classifier: Intended Audience :: Developers
Classifier: License :: OSI Approved :: BSD License
Classifier: Operating System :: OS Independent
Classifier: Programming Language :: Python
Classifier: Topic :: Software Development :: Libraries :: Python Modules
License-File: LICENSE
